couplet_composer/__init__.py
couplet_composer/__main__.py
couplet_composer/__version__.py
couplet_composer/args.py
couplet_composer/composing_mode.py
couplet_composer/configuring_mode.py
couplet_composer/dependency_set.py
couplet_composer/modes.py
couplet_composer/preset_mode.py
couplet_composer/run.py
couplet_composer/toolchain.py
couplet_composer/compose/__init__.py
couplet_composer/compose/libraries.py
couplet_composer/dependencies/__init__.py
couplet_composer/dependencies/_common.py
couplet_composer/dependencies/benchmark.py
couplet_composer/dependencies/cxxopts.py
couplet_composer/dependencies/glad.py
couplet_composer/dependencies/googletest.py
couplet_composer/dependencies/lua.py
couplet_composer/dependencies/sdl.py
couplet_composer/dependencies/spdlog.py
couplet_composer/dependencies/stb_image.py
couplet_composer/dependencies/lua/CMakeLists.txt
couplet_composer/github/__init__.py
couplet_composer/github/_api_v3.py
couplet_composer/github/_api_v4.py
couplet_composer/github/access.py
couplet_composer/github/release.py
couplet_composer/github/repository.py
couplet_composer/github/tag.py
couplet_composer/github/graphql/github_asset.graphql
couplet_composer/github/graphql/github_repository.graphql
couplet_composer/github/graphql/github_tag.graphql
couplet_composer/llvm/__init__.py
couplet_composer/llvm/run-clang-tidy.py
couplet_composer/support/__init__.py
couplet_composer/support/build_variant.py
couplet_composer/support/cmake_generators.py
couplet_composer/support/compiler_toolchains.py
couplet_composer/support/dependency_data.py
couplet_composer/support/dependency_install_information.py
couplet_composer/support/environment.py
couplet_composer/support/file_paths.py
couplet_composer/support/github_data.py
couplet_composer/support/mode_names.py
couplet_composer/support/platform_names.py
couplet_composer/support/presets.py
couplet_composer/support/project_names.py
couplet_composer/support/project_values.py
couplet_composer/support/tool_data.py
couplet_composer-1.9.0.dist-info/LICENCE
couplet_composer-1.9.0.dist-info/METADATA
couplet_composer-1.9.0.dist-info/WHEEL
couplet_composer-1.9.0.dist-info/entry_points.txt
couplet_composer-1.9.0.dist-info/top_level.txt
couplet_composer-1.9.0.dist-info/RECORD
