Metadata-Version: 2.1
Name: couplet-composer
Version: 1.9.0
Summary: Tool for building, testing, and preparing binary distribution archives of Obliging Ode and Unsung Anthem.
Home-page: https://github.com/anttikivi/couplet-composer
Author: Antti Kivi
Author-email: antti.kivi@visiosto.fi
License: MIT
Platform: UNKNOWN
Classifier: License :: OSI Approved :: MIT License
Classifier: Programming Language :: Python
Classifier: Programming Language :: Python :: 2
Classifier: Programming Language :: Python :: 2.7
Classifier: Programming Language :: Python :: 3
Classifier: Programming Language :: Python :: Implementation :: CPython
Classifier: Programming Language :: Python :: Implementation :: PyPy
Classifier: Operating System :: OS Independent
Requires-Python: >=2.7.11
Requires-Dist: distro (==1.5.0)
Requires-Dist: PyYAML (==5.4.1)
Requires-Dist: requests (==2.25.1)
